xarray_cube/__init__.py
xarray_cube/accessor.py
xarray_cube/converter.py
xarray_cube/cube.py
xarray_cube-0.3.1.dist-info/LICENSE
xarray_cube-0.3.1.dist-info/WHEEL
xarray_cube-0.3.1.dist-info/METADATA
xarray_cube-0.3.1.dist-info/RECORD
