Metadata-Version: 2.1
Name: xarray-cube
Version: 0.3.1
Summary: xarray extension for spectral cube analysis
Home-page: https://github.com/a-lab-nagoya/xarray-cube/
License: MIT
Author: Akio Taniguchi
Author-email: taniguchi@a.phys.nagoya-u.ac.jp
Requires-Python: >=3.7.1,<3.10
Classifier: License :: OSI Approved :: MIT License
Classifier: Programming Language :: Python :: 3
Classifier: Programming Language :: Python :: 3.8
Classifier: Programming Language :: Python :: 3.9
Requires-Dist: astropy (>=4.3,<5.0)
Requires-Dist: numpy (>=1.21,<2.0)
Requires-Dist: spectral-cube (>=0.6,<0.7)
Requires-Dist: typing-extensions (>=3.10,<4.0)
Requires-Dist: xarray (>=0.18,<0.30)
Requires-Dist: xarray-dataclasses (>=1.0,<2.0)
Project-URL: Documentation, https://a-lab-nagoya.github.io/xarray-cube/
